{
    "info": {
        "_postman_id": "club-pulse-api-v2",
        "name": "Club Pulse API v2.0",
        "description": "API Collection for Club Pulse System - High Performance Edition with Redis Integration",
        "schema": "https://schema.getpostman.com/json/collection/v2.1.0/collection.json"
    },
    "variable": [
        {
            "key": "baseUrl",
            "value": "http://localhost:8080/api/v1"
        },
        {
            "key": "token",
            "value": ""
        },
        {
            "key": "refreshToken",
            "value": ""
        },
        {
            "key": "userId",
            "value": ""
        },
        {
            "key": "facilityId",
            "value": ""
        },
        {
            "key": "bookingId",
            "value": ""
        },
        {
            "key": "tierId",
            "value": ""
        }
    ],
    "item": [
        {
            "name": "Health",
            "item": [
                {
                    "name": "Health Check",
                    "request": {
                        "method": "GET",
                        "header": [],
                        "url": {
                            "raw": "http://localhost:8080/health",
                            "protocol": "http",
                            "host": [
                                "localhost"
                            ],
                            "port": "8080",
                            "path": [
                                "health"
                            ]
                        }
                    },
                    "response": []
                }
            ]
        },
        {
            "name": "Auth",
            "item": [
                {
                    "name": "Login - Admin",
                    "event": [
                        {
                            "listen": "test",
                            "script": {
                                "exec": [
                                    "var jsonData = pm.response.json();",
                                    "if(jsonData.access_token) {",
                                    "    pm.collectionVariables.set('token', jsonData.access_token);",
                                    "    pm.collectionVariables.set('refreshToken', jsonData.refresh_token);",
                                    "}",
                                    "if(jsonData.user && jsonData.user.id) {",
                                    "    pm.collectionVariables.set('userId', jsonData.user.id);",
                                    "}"
                                ],
                                "type": "text/javascript"
                            }
                        }
                    ],
                    "request": {
                        "method": "POST",
                        "header": [
                            {
                                "key": "Content-Type",
                                "value": "application/json"
                            }
                        ],
                        "body": {
                            "mode": "raw",
                            "raw": "{\n  \"email\": \"admin@clubpulse.com\",\n  \"password\": \"admin123\"\n}"
                        },
                        "url": {
                            "raw": "{{baseUrl}}/auth/login",
                            "host": [
                                "{{baseUrl}}"
                            ],
                            "path": [
                                "auth",
                                "login"
                            ]
                        }
                    },
                    "response": []
                },
                {
                    "name": "Login - Test User",
                    "event": [
                        {
                            "listen": "test",
                            "script": {
                                "exec": [
                                    "var jsonData = pm.response.json();",
                                    "if(jsonData.access_token) {",
                                    "    pm.collectionVariables.set('token', jsonData.access_token);",
                                    "    pm.collectionVariables.set('refreshToken', jsonData.refresh_token);",
                                    "}",
                                    "if(jsonData.user && jsonData.user.id) {",
                                    "    pm.collectionVariables.set('userId', jsonData.user.id);",
                                    "}"
                                ],
                                "type": "text/javascript"
                            }
                        }
                    ],
                    "request": {
                        "method": "POST",
                        "header": [
                            {
                                "key": "Content-Type",
                                "value": "application/json"
                            }
                        ],
                        "body": {
                            "mode": "raw",
                            "raw": "{\n  \"email\": \"testuser@example.com\",\n  \"password\": \"password123\"\n}"
                        },
                        "url": {
                            "raw": "{{baseUrl}}/auth/login",
                            "host": [
                                "{{baseUrl}}"
                            ],
                            "path": [
                                "auth",
                                "login"
                            ]
                        }
                    },
                    "response": []
                },
                {
                    "name": "Register",
                    "request": {
                        "method": "POST",
                        "header": [
                            {
                                "key": "Content-Type",
                                "value": "application/json"
                            }
                        ],
                        "body": {
                            "mode": "raw",
                            "raw": "{\n  \"name\": \"Nuevo Usuario\",\n  \"email\": \"nuevo@example.com\",\n  \"password\": \"password123\"\n}"
                        },
                        "url": {
                            "raw": "{{baseUrl}}/auth/register",
                            "host": [
                                "{{baseUrl}}"
                            ],
                            "path": [
                                "auth",
                                "register"
                            ]
                        }
                    },
                    "response": []
                },
                {
                    "name": "Refresh Token",
                    "event": [
                        {
                            "listen": "test",
                            "script": {
                                "exec": [
                                    "var jsonData = pm.response.json();",
                                    "if(jsonData.access_token) {",
                                    "    pm.collectionVariables.set('token', jsonData.access_token);",
                                    "}"
                                ],
                                "type": "text/javascript"
                            }
                        }
                    ],
                    "request": {
                        "method": "POST",
                        "header": [
                            {
                                "key": "Content-Type",
                                "value": "application/json"
                            }
                        ],
                        "body": {
                            "mode": "raw",
                            "raw": "{\n  \"refresh_token\": \"{{refreshToken}}\"\n}"
                        },
                        "url": {
                            "raw": "{{baseUrl}}/auth/refresh",
                            "host": [
                                "{{baseUrl}}"
                            ],
                            "path": [
                                "auth",
                                "refresh"
                            ]
                        }
                    },
                    "response": []
                },
                {
                    "name": "Logout",
                    "request": {
                        "method": "POST",
                        "header": [
                            {
                                "key": "Authorization",
                                "value": "Bearer {{token}}"
                            }
                        ],
                        "url": {
                            "raw": "{{baseUrl}}/auth/logout",
                            "host": [
                                "{{baseUrl}}"
                            ],
                            "path": [
                                "auth",
                                "logout"
                            ]
                        }
                    },
                    "response": []
                },
                {
                    "name": "List Sessions",
                    "request": {
                        "method": "GET",
                        "header": [
                            {
                                "key": "Authorization",
                                "value": "Bearer {{token}}"
                            }
                        ],
                        "url": {
                            "raw": "{{baseUrl}}/auth/sessions",
                            "host": [
                                "{{baseUrl}}"
                            ],
                            "path": [
                                "auth",
                                "sessions"
                            ]
                        }
                    },
                    "response": []
                }
            ]
        },
        {
            "name": "Users",
            "item": [
                {
                    "name": "Get My Profile",
                    "request": {
                        "method": "GET",
                        "header": [
                            {
                                "key": "Authorization",
                                "value": "Bearer {{token}}"
                            }
                        ],
                        "url": {
                            "raw": "{{baseUrl}}/users/me",
                            "host": [
                                "{{baseUrl}}"
                            ],
                            "path": [
                                "users",
                                "me"
                            ]
                        }
                    },
                    "response": []
                },
                {
                    "name": "List Users",
                    "request": {
                        "method": "GET",
                        "header": [
                            {
                                "key": "Authorization",
                                "value": "Bearer {{token}}"
                            }
                        ],
                        "url": {
                            "raw": "{{baseUrl}}/users?limit=10&offset=0",
                            "host": [
                                "{{baseUrl}}"
                            ],
                            "path": [
                                "users"
                            ],
                            "query": [
                                {
                                    "key": "limit",
                                    "value": "10"
                                },
                                {
                                    "key": "offset",
                                    "value": "0"
                                }
                            ]
                        }
                    },
                    "response": []
                },
                {
                    "name": "Get User by ID",
                    "request": {
                        "method": "GET",
                        "header": [
                            {
                                "key": "Authorization",
                                "value": "Bearer {{token}}"
                            }
                        ],
                        "url": {
                            "raw": "{{baseUrl}}/users/{{userId}}",
                            "host": [
                                "{{baseUrl}}"
                            ],
                            "path": [
                                "users",
                                "{{userId}}"
                            ]
                        }
                    },
                    "response": []
                }
            ]
        },
        {
            "name": "Facilities",
            "item": [
                {
                    "name": "List Facilities",
                    "event": [
                        {
                            "listen": "test",
                            "script": {
                                "exec": [
                                    "var jsonData = pm.response.json();",
                                    "if(jsonData && jsonData.length > 0) {",
                                    "    pm.collectionVariables.set('facilityId', jsonData[0].id);",
                                    "}"
                                ],
                                "type": "text/javascript"
                            }
                        }
                    ],
                    "request": {
                        "method": "GET",
                        "header": [
                            {
                                "key": "Authorization",
                                "value": "Bearer {{token}}"
                            }
                        ],
                        "url": {
                            "raw": "{{baseUrl}}/facilities?limit=10&offset=0",
                            "host": [
                                "{{baseUrl}}"
                            ],
                            "path": [
                                "facilities"
                            ],
                            "query": [
                                {
                                    "key": "limit",
                                    "value": "10"
                                },
                                {
                                    "key": "offset",
                                    "value": "0"
                                }
                            ]
                        }
                    },
                    "response": []
                },
                {
                    "name": "Get Facility by ID",
                    "request": {
                        "method": "GET",
                        "header": [
                            {
                                "key": "Authorization",
                                "value": "Bearer {{token}}"
                            }
                        ],
                        "url": {
                            "raw": "{{baseUrl}}/facilities/{{facilityId}}",
                            "host": [
                                "{{baseUrl}}"
                            ],
                            "path": [
                                "facilities",
                                "{{facilityId}}"
                            ]
                        }
                    },
                    "response": []
                },
                {
                    "name": "Create Facility",
                    "request": {
                        "method": "POST",
                        "header": [
                            {
                                "key": "Authorization",
                                "value": "Bearer {{token}}"
                            },
                            {
                                "key": "Content-Type",
                                "value": "application/json"
                            }
                        ],
                        "body": {
                            "mode": "raw",
                            "raw": "{\n  \"name\": \"Nueva Cancha de Tenis\",\n  \"type\": \"court\",\n  \"status\": \"active\",\n  \"capacity\": 4,\n  \"hourly_rate\": 45.00,\n  \"location\": {\n    \"name\": \"Sector Norte\",\n    \"description\": \"Al lado del estacionamiento\"\n  },\n  \"specifications\": {\n    \"surface_type\": \"Clay Court\",\n    \"lighting\": true,\n    \"covered\": false,\n    \"equipment\": [\"net\", \"balls\"]\n  }\n}"
                        },
                        "url": {
                            "raw": "{{baseUrl}}/facilities",
                            "host": [
                                "{{baseUrl}}"
                            ],
                            "path": [
                                "facilities"
                            ]
                        }
                    },
                    "response": []
                }
            ]
        },
        {
            "name": "Memberships",
            "item": [
                {
                    "name": "List Tiers",
                    "event": [
                        {
                            "listen": "test",
                            "script": {
                                "exec": [
                                    "var jsonData = pm.response.json();",
                                    "if(jsonData && jsonData.length > 0) {",
                                    "    pm.collectionVariables.set('tierId', jsonData[0].id);",
                                    "}"
                                ],
                                "type": "text/javascript"
                            }
                        }
                    ],
                    "request": {
                        "method": "GET",
                        "header": [
                            {
                                "key": "Authorization",
                                "value": "Bearer {{token}}"
                            }
                        ],
                        "url": {
                            "raw": "{{baseUrl}}/memberships/tiers",
                            "host": [
                                "{{baseUrl}}"
                            ],
                            "path": [
                                "memberships",
                                "tiers"
                            ]
                        }
                    },
                    "response": []
                },
                {
                    "name": "Get Tier by ID",
                    "request": {
                        "method": "GET",
                        "header": [
                            {
                                "key": "Authorization",
                                "value": "Bearer {{token}}"
                            }
                        ],
                        "url": {
                            "raw": "{{baseUrl}}/memberships/tiers/{{tierId}}",
                            "host": [
                                "{{baseUrl}}"
                            ],
                            "path": [
                                "memberships",
                                "tiers",
                                "{{tierId}}"
                            ]
                        }
                    },
                    "response": []
                }
            ]
        },
        {
            "name": "Bookings",
            "item": [
                {
                    "name": "List Bookings",
                    "request": {
                        "method": "GET",
                        "header": [
                            {
                                "key": "Authorization",
                                "value": "Bearer {{token}}"
                            }
                        ],
                        "url": {
                            "raw": "{{baseUrl}}/bookings",
                            "host": [
                                "{{baseUrl}}"
                            ],
                            "path": [
                                "bookings"
                            ]
                        }
                    },
                    "response": []
                },
                {
                    "name": "Create Booking",
                    "event": [
                        {
                            "listen": "test",
                            "script": {
                                "exec": [
                                    "var jsonData = pm.response.json();",
                                    "if(jsonData && jsonData.id) {",
                                    "    pm.collectionVariables.set('bookingId', jsonData.id);",
                                    "}"
                                ],
                                "type": "text/javascript"
                            }
                        }
                    ],
                    "request": {
                        "method": "POST",
                        "header": [
                            {
                                "key": "Authorization",
                                "value": "Bearer {{token}}"
                            },
                            {
                                "key": "Content-Type",
                                "value": "application/json"
                            }
                        ],
                        "body": {
                            "mode": "raw",
                            "raw": "{\n  \"facility_id\": \"{{facilityId}}\",\n  \"start_time\": \"2025-01-15T10:00:00Z\",\n  \"end_time\": \"2025-01-15T11:00:00Z\"\n}"
                        },
                        "url": {
                            "raw": "{{baseUrl}}/bookings",
                            "host": [
                                "{{baseUrl}}"
                            ],
                            "path": [
                                "bookings"
                            ]
                        }
                    },
                    "response": []
                },
                {
                    "name": "Get Booking by ID",
                    "request": {
                        "method": "GET",
                        "header": [
                            {
                                "key": "Authorization",
                                "value": "Bearer {{token}}"
                            }
                        ],
                        "url": {
                            "raw": "{{baseUrl}}/bookings/{{bookingId}}",
                            "host": [
                                "{{baseUrl}}"
                            ],
                            "path": [
                                "bookings",
                                "{{bookingId}}"
                            ]
                        }
                    },
                    "response": []
                },
                {
                    "name": "Cancel Booking",
                    "request": {
                        "method": "PUT",
                        "header": [
                            {
                                "key": "Authorization",
                                "value": "Bearer {{token}}"
                            }
                        ],
                        "url": {
                            "raw": "{{baseUrl}}/bookings/{{bookingId}}/cancel",
                            "host": [
                                "{{baseUrl}}"
                            ],
                            "path": [
                                "bookings",
                                "{{bookingId}}",
                                "cancel"
                            ]
                        }
                    },
                    "response": []
                },
                {
                    "name": "Check Availability",
                    "request": {
                        "method": "GET",
                        "header": [
                            {
                                "key": "Authorization",
                                "value": "Bearer {{token}}"
                            }
                        ],
                        "url": {
                            "raw": "{{baseUrl}}/bookings/availability?facility_id={{facilityId}}&date=2025-01-15",
                            "host": [
                                "{{baseUrl}}"
                            ],
                            "path": [
                                "bookings",
                                "availability"
                            ],
                            "query": [
                                {
                                    "key": "facility_id",
                                    "value": "{{facilityId}}"
                                },
                                {
                                    "key": "date",
                                    "value": "2025-01-15"
                                }
                            ]
                        }
                    },
                    "response": []
                }
            ]
        }
    ]
}